japanese_dictionary_parser/__init__.py
japanese_dictionary_parser/parsers.py
japanese_dictionary_parser/parsing_utils/__init__.py
japanese_dictionary_parser/parsing_utils/helper.py
japanese_dictionary_parser/parsing_utils/jmdict_parser.py
japanese_dictionary_parser/parsing_utils/kanjidic2_parser.py
japanese_dictionary_parser/parsing_utils/parsing_dataclass/__init__.py
japanese_dictionary_parser/parsing_utils/parsing_dataclass/baseclass_dataclass.py
japanese_dictionary_parser/parsing_utils/parsing_dataclass/get_error_wrapper.py
japanese_dictionary_parser/parsing_utils/parsing_dataclass/jmdict_dataclass.py
japanese_dictionary_parser/parsing_utils/parsing_dataclass/kanjidic2_dataclass.py
japanese_dictionary_parser-0.1.2.dist-info/LICENSE
japanese_dictionary_parser-0.1.2.dist-info/WHEEL
japanese_dictionary_parser-0.1.2.dist-info/METADATA
japanese_dictionary_parser-0.1.2.dist-info/RECORD
